miavisc/__init__.py
miavisc/cli.py
miavisc/hash_utils.py
miavisc/pdf.py
miavisc/processing.py
miavisc/settings.py
miavisc/video.py
miavisc-2.0.0.dist-info/METADATA
miavisc-2.0.0.dist-info/WHEEL
miavisc-2.0.0.dist-info/entry_points.txt
miavisc-2.0.0.dist-info/licenses/LICENSE
miavisc-2.0.0.dist-info/RECORD
