Metadata-Version: 2.4
Name: miavisc
Version: 2.0.0
Summary: Miavisc is a video → slide converter
Project-URL: Repository, https://github.com/pannxe/miavisc.git
Project-URL: Issues, https://github.com/pannxe/miavisc/issues
Project-URL: GitHub, https://github.com/pannxe/miavisc
License-File: LICENSE
Keywords: converter,extract,lecture,slide,video
Classifier: Development Status :: 4 - Beta
Classifier: Environment :: Console
Classifier: Intended Audience :: Education
Classifier: License :: OSI Approved :: MIT License
Classifier: Operating System :: OS Independent
Classifier: Programming Language :: Python :: 3
Classifier: Topic :: Multimedia :: Video :: Capture
Classifier: Topic :: Utilities
Requires-Python: >=3.12
Requires-Dist: av>=14.4.0
Requires-Dist: imagehash>=4.3.2
Requires-Dist: imageio>=2.37.0
Requires-Dist: img2pdf>=0.6.1
Requires-Dist: opencv-contrib-python>=4.11.0.86
Requires-Dist: pillow>=11.2.1
